{
  "generated_at": "2026-01-06T08:41:49Z",
  "results": [
    {
      "name": "portfolio",
      "url": "https://remiel.work",
      "timestamp": "2026-01-06T08:41:43Z",
      "up": true,
      "status": 200,
      "latency_ms": 972
    },
    {
      "name": "backend server",
      "url": "https://api.remiel.work",
      "timestamp": "2026-01-06T08:41:48Z",
      "up": false,
      "status": 404,
      "latency_ms": 4609
    },
    {
      "name": "github projects",
      "url": "https://github.remiel.work",
      "timestamp": "2026-01-06T08:41:48Z",
      "up": true,
      "status": 200,
      "latency_ms": 178
    },
    {
      "name": "sanjeevi porfolio",
      "url": "https://sanjeevi.cv",
      "timestamp": "2026-01-06T08:41:49Z",
      "up": true,
      "status": 200,
      "latency_ms": 729
    }
  ]
}