{
  "generated_at": "2026-02-09T17:18:09Z",
  "results": [
    {
      "name": "portfolio",
      "url": "https://remiel.work",
      "timestamp": "2026-02-09T17:18:08Z",
      "up": true,
      "status": 200,
      "latency_ms": 207
    },
    {
      "name": "github projects",
      "url": "https://github.remiel.work",
      "timestamp": "2026-02-09T17:18:09Z",
      "up": true,
      "status": 200,
      "latency_ms": 113
    },
    {
      "name": "sanjeevi porfolio",
      "url": "https://sanjeevi.cv",
      "timestamp": "2026-02-09T17:18:09Z",
      "up": true,
      "status": 200,
      "latency_ms": 395
    }
  ]
}