{
  "generated_at": "2026-01-12T13:59:08Z",
  "results": [
    {
      "name": "portfolio",
      "url": "https://remiel.work",
      "timestamp": "2026-01-12T13:59:01Z",
      "up": true,
      "status": 200,
      "latency_ms": 557
    },
    {
      "name": "backend server",
      "url": "https://api.remiel.work",
      "timestamp": "2026-01-12T13:59:07Z",
      "up": false,
      "status": 404,
      "latency_ms": 6349
    },
    {
      "name": "github projects",
      "url": "https://github.remiel.work",
      "timestamp": "2026-01-12T13:59:07Z",
      "up": true,
      "status": 200,
      "latency_ms": 307
    },
    {
      "name": "sanjeevi porfolio",
      "url": "https://sanjeevi.cv",
      "timestamp": "2026-01-12T13:59:08Z",
      "up": true,
      "status": 200,
      "latency_ms": 677
    }
  ]
}