{
  "generated_at": "2025-12-03T04:41:22Z",
  "results": [
    {
      "name": "portfolio",
      "url": "https://remiel.work",
      "timestamp": "2025-12-03T04:41:17Z",
      "up": true,
      "status": 200,
      "latency_ms": 563
    },
    {
      "name": "backend server",
      "url": "https://api.remiel.work",
      "timestamp": "2025-12-03T04:41:21Z",
      "up": false,
      "status": 404,
      "latency_ms": 4073
    },
    {
      "name": "github projects",
      "url": "https://github.remiel.work",
      "timestamp": "2025-12-03T04:41:21Z",
      "up": true,
      "status": 200,
      "latency_ms": 172
    },
    {
      "name": "sanjeevi porfolio",
      "url": "https://sanjeevi.cv",
      "timestamp": "2025-12-03T04:41:22Z",
      "up": true,
      "status": 200,
      "latency_ms": 785
    }
  ]
}