{
  "generated_at": "2025-12-08T21:59:56Z",
  "results": [
    {
      "name": "portfolio",
      "url": "https://remiel.work",
      "timestamp": "2025-12-08T21:59:52Z",
      "up": true,
      "status": 200,
      "latency_ms": 659
    },
    {
      "name": "backend server",
      "url": "https://api.remiel.work",
      "timestamp": "2025-12-08T21:59:55Z",
      "up": false,
      "status": 404,
      "latency_ms": 2550
    },
    {
      "name": "github projects",
      "url": "https://github.remiel.work",
      "timestamp": "2025-12-08T21:59:55Z",
      "up": true,
      "status": 200,
      "latency_ms": 280
    },
    {
      "name": "sanjeevi porfolio",
      "url": "https://sanjeevi.cv",
      "timestamp": "2025-12-08T21:59:56Z",
      "up": true,
      "status": 200,
      "latency_ms": 909
    }
  ]
}