{
  "generated_at": "2025-12-01T04:57:22Z",
  "results": [
    {
      "name": "portfolio",
      "url": "https://remiel.work",
      "timestamp": "2025-12-01T04:57:14Z",
      "up": true,
      "status": 200,
      "latency_ms": 830
    },
    {
      "name": "backend server",
      "url": "https://api.remiel.work",
      "timestamp": "2025-12-01T04:57:21Z",
      "up": false,
      "status": 404,
      "latency_ms": 6830
    },
    {
      "name": "github projects",
      "url": "https://github.remiel.work",
      "timestamp": "2025-12-01T04:57:21Z",
      "up": true,
      "status": 200,
      "latency_ms": 204
    },
    {
      "name": "sanjeevi porfolio",
      "url": "https://sanjeevi.cv",
      "timestamp": "2025-12-01T04:57:22Z",
      "up": true,
      "status": 200,
      "latency_ms": 919
    }
  ]
}