{
  "generated_at": "2026-02-15T12:53:00Z",
  "results": [
    {
      "name": "portfolio",
      "url": "https://remiel.work",
      "timestamp": "2026-02-15T12:53:00Z",
      "up": true,
      "status": 200,
      "latency_ms": 539
    },
    {
      "name": "github projects",
      "url": "https://github.remiel.work",
      "timestamp": "2026-02-15T12:53:00Z",
      "up": true,
      "status": 200,
      "latency_ms": 120
    },
    {
      "name": "sanjeevi porfolio",
      "url": "https://sanjeevi.cv",
      "timestamp": "2026-02-15T12:53:00Z",
      "up": true,
      "status": 200,
      "latency_ms": 260
    }
  ]
}